jirawiki2docx/__init__.py
jirawiki2docx/jirawiki2docx.py
jirawiki2docx-1.0.1.dist-info/LICENSE
jirawiki2docx-1.0.1.dist-info/METADATA
jirawiki2docx-1.0.1.dist-info/WHEEL
jirawiki2docx-1.0.1.dist-info/top_level.txt
jirawiki2docx-1.0.1.dist-info/RECORD
