Metadata-Version: 2.1
Name: jirawiki2docx
Version: 1.0.1
Summary: Convert Jira wiki to DOCX format effectively
Home-page: https://github.com/deitar/jirawiki2docx
Author: Ifeoluwa Akande
Author-email: 
Project-URL: Bug Tracker, https://github.com/deitar/jirawiki2docx/issues
Project-URL: repository, https://github.com/deitar/jirawiki2docx
Classifier: Development Status :: 5 - Production/Stable
Classifier: Programming Language :: Python :: 3
Classifier: License :: OSI Approved :: MIT License
Classifier: Operating System :: OS Independent
Classifier: Topic :: Office/Business :: Office Suites
Classifier: Topic :: Software Development :: Libraries
Requires-Python: >=3.7
License-File: LICENSE
Requires-Dist: python-docx (>=0.8.11)
Requires-Dist: webcolors (>=1.13)
